terraform_cloud_okta_warden/__init__.py
terraform_cloud_okta_warden/__main__.py
terraform_cloud_okta_warden/config.py
terraform_cloud_okta_warden/okta.py
terraform_cloud_okta_warden/py.typed
terraform_cloud_okta_warden/terraform_cloud.py
terraform_cloud_okta_warden-0.2.0.dist-info/LICENSE
terraform_cloud_okta_warden-0.2.0.dist-info/METADATA
terraform_cloud_okta_warden-0.2.0.dist-info/WHEEL
terraform_cloud_okta_warden-0.2.0.dist-info/entry_points.txt
terraform_cloud_okta_warden-0.2.0.dist-info/RECORD
