Metadata-Version: 2.1
Name: terraform-cloud-okta-warden
Version: 0.2.0
Summary: Terraform Cloud Okta Warden
Home-page: https://github.com/ninadpage/terraform-cloud-okta-warden
License: Apache-2.0
Author: Ninad Page
Author-email: ninadpage@users.noreply.github.com
Requires-Python: >=3.10,<4.0
Classifier: Development Status :: 3 - Alpha
Classifier: License :: OSI Approved :: Apache Software License
Classifier: Programming Language :: Python :: 3
Classifier: Programming Language :: Python :: 3.10
Classifier: Programming Language :: Python :: 3.11
Classifier: Programming Language :: Python :: 3.12
Requires-Dist: coloredlogs (>=15.0,<16.0)
Requires-Dist: okta (>=2.9.5,<3.0.0)
Requires-Dist: pydantic-settings (>=2.1.0,<3.0.0)
Requires-Dist: terrasnek (>=0.1.13,<0.2.0)
Requires-Dist: typer (>=0.9,<0.10)
Project-URL: Changelog, https://github.com/ninadpage/terraform-cloud-okta-warden/releases
Project-URL: Repository, https://github.com/ninadpage/terraform-cloud-okta-warden
